{
  "task": "single_rotation",
  "seed": 1,
  "anchor": "randomconv",
  "true_families": [
    "rotate"
  ],
  "hidden": [
    2
  ],
  "valid_ref_validity": -8.384015083312988,
  "decoy_ref_validity": -8.433761596679688,
  "arms": {
    "BASE_IDENTITY": {
      "collapse_validity": {
        "move_pixel": 0.0,
        "identity_collapse": true,
        "mean_validity": -5.90659761428833,
        "validity_rate": 0.92578125,
        "anchor_ed": 0.22760677337646484
      },
      "coverage": {
        "heldout_coverage": 0.0,
        "reachable_spread": 0.0
      },
      "latent_recovery": {
        "moved_per_factor": {
          "cx": 0.0,
          "cy": 0.0,
          "rot": 0.0,
          "scale": 0.0,
          "hue": 0.0,
          "bright": 0.0,
          "stroke": 0.0,
          "bg": 0.0
        },
        "hidden_factor_mass": 0.0
      }
    },
    "KNOWN_ORACLE": {
      "collapse_validity": {
        "move_pixel": 5.32833194732666,
        "identity_collapse": false,
        "mean_validity": -5.520986080169678,
        "validity_rate": 0.97265625,
        "anchor_ed": 0.10949897766113281
      },
      "coverage": {
        "heldout_coverage": 1.0,
        "heldout_coverage_joint": 1.0,
        "per_factor_coverage": {
          "rot": 1.0
        },
        "reachable_spread": 0.9432619214057922
      },
      "latent_recovery": {
        "moved_per_factor": {
          "cx": 0.0,
          "cy": 0.0,
          "rot": 0.9046245217323303,
          "scale": 0.0,
          "hue": 0.0,
          "bright": 0.0,
          "stroke": 0.0,
          "bg": 0.0
        },
        "hidden_factor_mass": 1.0
      }
    },
    "RANDOM_VALID_POLICY": {
      "collapse_validity": {
        "move_pixel": 7.095621109008789,
        "identity_collapse": false,
        "mean_validity": -8.22230052947998,
        "validity_rate": 0.57421875,
        "anchor_ed": 0.38400745391845703
      },
      "coverage": {
        "heldout_coverage": 1.0,
        "heldout_coverage_joint": 1.0,
        "per_factor_coverage": {
          "rot": 1.0
        },
        "reachable_spread": 0.3667728304862976
      },
      "latent_recovery": {
        "moved_per_factor": {
          "cx": 0.03420842066407204,
          "cy": 0.03214772045612335,
          "rot": 0.13759702444076538,
          "scale": 0.032355573028326035,
          "hue": 0.050245173275470734,
          "bright": 0.029357125982642174,
          "stroke": 0.04270891472697258,
          "bg": 0.0
        },
        "hidden_factor_mass": 0.3836847930769385
      }
    },
    "RANDOM_WITH_DECOYS": {
      "collapse_validity": {
        "move_pixel": 7.9759626388549805,
        "identity_collapse": false,
        "mean_validity": -8.324902534484863,
        "validity_rate": 0.5546875,
        "anchor_ed": 0.7309703826904297
      },
      "coverage": {
        "heldout_coverage": 1.0,
        "heldout_coverage_joint": 1.0,
        "per_factor_coverage": {
          "rot": 1.0
        },
        "reachable_spread": 0.29709136486053467
      },
      "latent_recovery": {
        "moved_per_factor": {
          "cx": 0.018263254314661026,
          "cy": 0.020567715167999268,
          "rot": 0.062377914786338806,
          "scale": 0.017728151753544807,
          "hue": 0.02889132685959339,
          "bright": 0.01725560426712036,
          "stroke": 0.022189466282725334,
          "bg": 0.0
        },
        "hidden_factor_mass": 0.3330846801978531
      }
    },
    "LEARNED_SINGLE_POLICY": {
      "quality": {
        "effective_usage": {
          "translate_x": 0.0,
          "translate_y": 0.0,
          "rotate": 1.0,
          "scale": 0.0,
          "hue": 0.0,
          "bright": 0.0,
          "stroke": 0.0,
          "crop_erase": 0.0,
          "big_shear": 0.0,
          "bg_shortcut": 0.0,
          "shape_warp": 0.0,
          "occlude": 0.0,
          "color_collapse": 0.0
        },
        "decoy_usage": 0.0,
        "true_family_usage": 1.0,
        "true_family_recall": 1.0,
        "true_families_recalled": [
          "rotate"
        ],
        "family_entropy": -0.0,
        "max_family_weight": 1.0,
        "top_family": "rotate"
      },
      "discover_final": {
        "L_anchor": 0.11868667602539062,
        "move": 6.398553848266602,
        "L_move": 0.0,
        "L_bound": 0.0023799538612365723,
        "fam_entropy": 0.4453496038913727
      },
      "collapse_validity": {
        "move_pixel": 4.6181535720825195,
        "identity_collapse": false,
        "mean_validity": -5.487338542938232,
        "validity_rate": 0.96875,
        "anchor_ed": 0.08100223541259766
      },
      "coverage": {
        "heldout_coverage": 1.0,
        "heldout_coverage_joint": 1.0,
        "per_factor_coverage": {
          "rot": 1.0
        },
        "reachable_spread": 0.7482123970985413
      },
      "latent_recovery": {
        "moved_per_factor": {
          "cx": 0.0,
          "cy": 0.0,
          "rot": 0.6831309795379639,
          "scale": 0.0,
          "hue": 0.0,
          "bright": 0.0,
          "stroke": 0.0,
          "bg": 0.0
        },
        "hidden_factor_mass": 1.0
      }
    },
    "LEARNED_MULTI_POLICY": {
      "quality": {
        "effective_usage": {
          "translate_x": 0.00606096675619483,
          "translate_y": 0.0008319892804138362,
          "rotate": 0.9302490949630737,
          "scale": 0.011356198228895664,
          "hue": 9.41543621593155e-05,
          "bright": 0.04905812069773674,
          "stroke": 0.002010510303080082,
          "crop_erase": 2.0810008209082298e-05,
          "big_shear": 9.23145780689083e-05,
          "bg_shortcut": 3.776059747906402e-05,
          "shape_warp": 0.00015558114682789892,
          "occlude": 0.0,
          "color_collapse": 3.235713666072115e-05
        },
        "decoy_usage": 0.0003388234672456747,
        "true_family_usage": 0.9302490949630737,
        "true_family_recall": 1.0,
        "true_families_recalled": [
          "rotate"
        ],
        "family_entropy": 0.44504842162132263,
        "max_family_weight": 0.9112703204154968,
        "top_family": "rotate"
      },
      "discover_final": {
        "L_anchor": 0.11868667602539062,
        "move": 6.398553848266602,
        "L_move": 0.0,
        "L_bound": 0.0023799538612365723,
        "fam_entropy": 0.4453496038913727
      },
      "collapse_validity": {
        "move_pixel": 4.59835147857666,
        "identity_collapse": false,
        "mean_validity": -5.830732822418213,
        "validity_rate": 0.94140625,
        "anchor_ed": 0.06931781768798828
      },
      "coverage": {
        "heldout_coverage": 1.0,
        "heldout_coverage_joint": 1.0,
        "per_factor_coverage": {
          "rot": 1.0
        },
        "reachable_spread": 0.7094127535820007
      },
      "latent_recovery": {
        "moved_per_factor": {
          "cx": 0.0029839682392776012,
          "cy": 0.00225949939340353,
          "rot": 0.640792727470398,
          "scale": 0.0011797863990068436,
          "hue": 0.0,
          "bright": 0.0019615991041064262,
          "stroke": 0.0002996764669660479,
          "bg": 0.0
        },
        "hidden_factor_mass": 0.9866283617345548
      }
    },
    "LEARNED_MULTI_NO_ANCHOR": {
      "quality": {
        "effective_usage": {
          "translate_x": 0.0,
          "translate_y": 0.0,
          "rotate": 0.0,
          "scale": 0.0,
          "hue": 0.0,
          "bright": 0.0,
          "stroke": 0.0,
          "crop_erase": 0.0,
          "big_shear": 0.0,
          "bg_shortcut": 0.0,
          "shape_warp": 0.0,
          "occlude": 0.0,
          "color_collapse": 0.0
        },
        "decoy_usage": 0.0,
        "true_family_usage": 0.0,
        "true_family_recall": 0.0,
        "true_families_recalled": [],
        "family_entropy": 2.5649280548095703,
        "max_family_weight": 0.07735735177993774,
        "top_family": "translate_x"
      },
      "discover_final": {
        "move": 6.25289249420166,
        "L_move": 0.0,
        "L_bound": 0.0,
        "fam_entropy": 2.56492018699646
      },
      "collapse_validity": {
        "move_pixel": 5.029662132263184,
        "identity_collapse": false,
        "mean_validity": -7.150347709655762,
        "validity_rate": 0.71875,
        "anchor_ed": 0.37514686584472656
      },
      "coverage": {
        "heldout_coverage": 0.921875,
        "heldout_coverage_joint": 0.921875,
        "per_factor_coverage": {
          "rot": 0.921875
        },
        "reachable_spread": 0.15018145740032196
      },
      "latent_recovery": {
        "moved_per_factor": {
          "cx": 0.007407424971461296,
          "cy": 0.006981855258345604,
          "rot": 0.025605972856283188,
          "scale": 0.006542190909385681,
          "hue": 0.010843775235116482,
          "bright": 0.0060295178554952145,
          "stroke": 0.00790288858115673,
          "bg": 0.0
        },
        "hidden_factor_mass": 0.3590614667297425
      }
    },
    "LEARNED_MULTI_NO_DIVERSITY": {
      "quality": {
        "effective_usage": {
          "translate_x": 0.0003272176836617291,
          "translate_y": 0.002772554522380233,
          "rotate": 0.9934895038604736,
          "scale": 0.0008654560660943389,
          "hue": 3.23509011650458e-05,
          "bright": 0.001778272446244955,
          "stroke": 0.0006311762263067067,
          "crop_erase": 1.793651608750224e-05,
          "big_shear": 3.236268457840197e-05,
          "bg_shortcut": 2.0445906557142735e-05,
          "shape_warp": 2.1847210518899374e-05,
          "occlude": 0.0,
          "color_collapse": 1.0811176252900623e-05
        },
        "decoy_usage": 0.00010340349399484694,
        "true_family_usage": 0.9934895038604736,
        "true_family_recall": 1.0,
        "true_families_recalled": [
          "rotate"
        ],
        "family_entropy": 0.00905921682715416,
        "max_family_weight": 0.999053418636322,
        "top_family": "rotate"
      },
      "discover_final": {
        "L_anchor": 0.1278820037841797,
        "move": 6.551980018615723,
        "L_move": 0.0,
        "L_bound": 0.005420299246907234
      },
      "collapse_validity": {
        "move_pixel": 4.8319244384765625,
        "identity_collapse": false,
        "mean_validity": -5.506117820739746,
        "validity_rate": 0.9609375,
        "anchor_ed": 0.08463859558105469
      },
      "coverage": {
        "heldout_coverage": 1.0,
        "heldout_coverage_joint": 1.0,
        "per_factor_coverage": {
          "rot": 1.0
        },
        "reachable_spread": 0.8055600523948669
      },
      "latent_recovery": {
        "moved_per_factor": {
          "cx": 3.6622681363951415e-05,
          "cy": 0.0,
          "rot": 0.7069497108459473,
          "scale": 5.077933383290656e-05,
          "hue": 0.0,
          "bright": 5.124395465827547e-05,
          "stroke": 0.0,
          "bg": 0.0
        },
        "hidden_factor_mass": 0.9998039277503263
      }
    },
    "LEARNED_MULTI_NO_BOUNDS": {
      "quality": {
        "effective_usage": {
          "translate_x": 0.031186359003186226,
          "translate_y": 0.0170381311327219,
          "rotate": 0.8444588780403137,
          "scale": 0.02697967179119587,
          "hue": 0.00015598851314280182,
          "bright": 0.07647857069969177,
          "stroke": 0.003202792489901185,
          "crop_erase": 3.3491953217890114e-05,
          "big_shear": 0.00014487373118754476,
          "bg_shortcut": 6.323541310848668e-05,
          "shape_warp": 0.00020688424410764128,
          "occlude": 0.0,
          "color_collapse": 5.1137358241248876e-05
        },
        "decoy_usage": 0.0004996226998628117,
        "true_family_usage": 0.8444588780403137,
        "true_family_recall": 1.0,
        "true_families_recalled": [
          "rotate"
        ],
        "family_entropy": 0.4418724477291107,
        "max_family_weight": 0.9121316075325012,
        "top_family": "rotate"
      },
      "discover_final": {
        "L_anchor": 0.11824417114257812,
        "move": 6.509429931640625,
        "L_move": 0.0,
        "fam_entropy": 0.44270819425582886
      },
      "collapse_validity": {
        "move_pixel": 4.782930374145508,
        "identity_collapse": false,
        "mean_validity": -5.805300235748291,
        "validity_rate": 0.92578125,
        "anchor_ed": 0.07178211212158203
      },
      "coverage": {
        "heldout_coverage": 1.0,
        "heldout_coverage_joint": 1.0,
        "per_factor_coverage": {
          "rot": 1.0
        },
        "reachable_spread": 0.7212437391281128
      },
      "latent_recovery": {
        "moved_per_factor": {
          "cx": 0.0024343617260456085,
          "cy": 0.0022829361259937286,
          "rot": 0.610930323600769,
          "scale": 0.0018183384090662003,
          "hue": 0.0,
          "bright": 0.0032889500726014376,
          "stroke": 0.00034895417047664523,
          "bg": 0.0
        },
        "hidden_factor_mass": 0.9836201970865976
      }
    }
  }
}