{
  "experiment_name": "q202_cd_langevin",
  "description": "IRED-CD Investigation - Stage 1: CD loss + Langevin sampling",
  "investigation": "ired-cd",
  "ablation_stage": "cd_langevin",
  "mining_strategy": "cd_langevin",
  "rank": 20,
  "ood": false,
  "diffusion_steps": 10,
  "batch_size": 2048,
  "train_steps": 100000,
  "learning_rate": 0.0001,
  "mining_opt_steps": 10,
  "mining_noise_scale": 1.5,
  "langevin_sigma_multiplier": 1.0,
  "use_langevin": true,
  "use_replay_buffer": false,
  "use_cd_loss": true,
  "use_residual_filter": false,
  "use_energy_schedule": false,
  "energy_loss_weight": 0.05,
  "output_dir": "results/ds_inverse/q202_cd_langevin",
  "notes": "Ablation 1: Corrected CD loss (detach x_neg, NOT energy_neg). Langevin noise sigma=sqrt(2*eta). k=10 steps. No replay buffer yet."
}
